bitparidade.v
module bitparidade (
    input wire B1, B2, B3, B4, B5, bitparidade,
    output reg saida
);
    always @(*) begin

        
        // Calculando o bit de paridade
        if (bitparidade == (B1 ^ B2 ^ B3 ^ B4 ^ B5)) begin
            saida = 1'b1; // Igualdade confirmada
        end else begin
            saida = 1'b0; // Igualdade não confirmada
        end
    end
endmodule

tp.v
`include "bitparidade.v"
module boolean_expression_initial (
    input wire B1, B2, B3, B4, B5, 
    input wire bitparidade, 
    output wire saida, 
    output reg Y1, Y2, Y3, Y4, Y5, Y6, Y7
    
);
    // Instanciando o módulo PARIDADE
    bitparidade U_PARIDADE (
        .B1(B1), 
        .B2(B2), 
        .B3(B3), 
        .B4(B4), 
        .B5(B5), 
        .bitparidade(bitparidade), 
        .saida(saida)
    );


    always @(*) begin
        if (saida == 1'b1) begin
            // Expressões booleanas para LEDs (Y1 a Y7)
            Y1 = (~B2 & ~B3 & ~B4 & ~B5) | (~B1 & ~B4 & B5) | (~B2 & B4 & B5) | (B3 & B4) | (B1 & ~B5);
            Y2 = (~B2 & ~B4) | (~B2 & ~B5) | (~B3 & ~B5 & ~B4) | (B2 & B3 & B5) | (B1);
            Y3 = (~B4 & B5) | (~B2 & B4 & ~B5) | (B3) | (B2 & ~B4) | (B2 & B5) | (B1);
            Y4 = (B4 & ~B5) | (B3 & ~B4 & B5) | (B2 & B5) | (B1);
            Y5 = (~B1 & ~B2) | (~B1 & ~B3 & ~B5) | (~B2 & B4 & ~B5) | (~B1 & B4 & B5);
            Y6 = (~B1 & ~B2 & ~B4) | (~B2 & ~B3 & B5) | (~B4 & B5) | (B3 & B4 & ~B5) | (B2 & ~B3 & ~B5) | (B2 & B3 & ~B4) | (B1 & B4);
            Y7 = (~B2 & ~B3) | ~B4 | (B2 & B3 & ~B5);
        end else begin
            // Valores padrão quando `saida` é 0
            Y1 = 1'b0;
            Y2 = 1'b0;
            Y3 = 1'b0;
            Y4 = 1'b0;
            Y5 = 1'b0;
            Y6 = 1'b0;
            Y7 = 1'b1;
        end
    end
endmodule

teste.v
`timescale 1ns/1ps

`include "tp.v"

module testebench;
    // Sinais de teste
    reg B1, B2, B3, B4, B5, bitparidade; 
    wire saida, Y1, Y2, Y3, Y4, Y5, Y6, Y7;

    // Instância do módulo sendo testado
    boolean_expression_initial uut (
        .B1(B1), 
        .B2(B2), 
        .B3(B3), 
        .B4(B4), 
        .B5(B5), 
        .bitparidade(bitparidade), 
        .saida(saida), 
        .Y1(Y1), 
        .Y2(Y2), 
        .Y3(Y3), 
        .Y4(Y4), 
        .Y5(Y5), 
        .Y6(Y6), 
        .Y7(Y7)
    );



    initial begin
        $dumpfile("boolean_expression.vcd"); 
        $dumpvars(0, testebench);
        

        $monitor("Time=%0t | B1=%b B2=%b B3=%b B4=%b B5=%b bitparidade=%b | Saida=%b | Y1=%b Y2=%b Y3=%b Y4=%b Y5=%b Y6=%b Y7=%b",
                 $time, B1, B2, B3, B4, B5, bitparidade, saida, Y1, Y2, Y3, Y4, Y5, Y6, Y7);

        // Casos de teste
        B1 = 0; B2 = 0; B3 = 0; B4 = 0; B5 = 0; bitparidade = 0; #100;
        B1 = 0; B2 = 0; B3 = 0; B4 = 0; B5 = 1; bitparidade = 1; #100;
        B1 = 0; B2 = 0; B3 = 0; B4 = 1; B5 = 0; bitparidade = 1; #100;
        B1 = 0; B2 = 0; B3 = 0; B4 = 1; B5 = 1; bitparidade = 0; #100;
        B1 = 0; B2 = 0; B3 = 1; B4 = 0; B5 = 0; bitparidade = 1; #100;
        B1 = 0; B2 = 0; B3 = 1; B4 = 0; B5 = 1; bitparidade = 0; #100;
        B1 = 0; B2 = 0; B3 = 1; B4 = 1; B5 = 0; bitparidade = 0; #100;
        B1 = 0; B2 = 0; B3 = 1; B4 = 1; B5 = 1; bitparidade = 1; #100;
        B1 = 0; B2 = 1; B3 = 0; B4 = 0; B5 = 0; bitparidade = 1; #100;
        B1 = 0; B2 = 1; B3 = 0; B4 = 0; B5 = 1; bitparidade = 0; #100;
        B1 = 0; B2 = 1; B3 = 0; B4 = 1; B5 = 0; bitparidade = 0; #100;
        B1 = 0; B2 = 1; B3 = 0; B4 = 1; B5 = 1; bitparidade = 1; #100;
        B1 = 0; B2 = 1; B3 = 1; B4 = 0; B5 = 0; bitparidade = 0; #100;
        B1 = 0; B2 = 1; B3 = 1; B4 = 0; B5 = 1; bitparidade = 1; #100;
        B1 = 0; B2 = 1; B3 = 1; B4 = 1; B5 = 0; bitparidade = 1; #100;
        B1 = 0; B2 = 1; B3 = 1; B4 = 1; B5 = 1; bitparidade = 0; #100;
        B1 = 1; B2 = 0; B3 = 0; B4 = 0; B5 = 0; bitparidade = 1; #100;
        B1 = 1; B2 = 0; B3 = 0; B4 = 0; B5 = 1; bitparidade = 0; #100;
        B1 = 1; B2 = 0; B3 = 0; B4 = 1; B5 = 0; bitparidade = 0; #100;
        B1 = 1; B2 = 0; B3 = 0; B4 = 1; B5 = 1; bitparidade = 1; #100;
        B1 = 1; B2 = 1; B3 = 1; B4 = 1; B5 = 1; bitparidade = 0; #100; // bitparidade errado
        B1 = 1; B2 = 0; B3 = 1; B4 = 0; B5 = 0; bitparidade = 1; #100;//bitparidade errado
        B1 = 1; B2 = 0; B3 = 1; B4 = 0; B5 = 1; bitparidade = 0; #100;
        $finish;
    end
endmodule

build/boolean_expression.vcd
$date
	Tue Nov 26 16:54:49 2024
$end
$version
	Icarus Verilog
$end
$timescale
	1ps
$end
$scope module testebench $end
$var wire 1 ! saida $end
$var wire 1 " Y7 $end
$var wire 1 # Y6 $end
$var wire 1 $ Y5 $end
$var wire 1 % Y4 $end
$var wire 1 & Y3 $end
$var wire 1 ' Y2 $end
$var wire 1 ( Y1 $end
$var reg 1 ) B1 $end
$var reg 1 * B2 $end
$var reg 1 + B3 $end
$var reg 1 , B4 $end
$var reg 1 - B5 $end
$var reg 1 . bitparidade $end
$scope module uut $end
$var wire 1 ) B1 $end
$var wire 1 * B2 $end
$var wire 1 + B3 $end
$var wire 1 , B4 $end
$var wire 1 - B5 $end
$var wire 1 . bitparidade $end
$var wire 1 ! saida $end
$var reg 1 ( Y1 $end
$var reg 1 ' Y2 $end
$var reg 1 & Y3 $end
$var reg 1 % Y4 $end
$var reg 1 $ Y5 $end
$var reg 1 # Y6 $end
$var reg 1 " Y7 $end
$scope module U_PARIDADE $end
$var wire 1 ) B1 $end
$var wire 1 * B2 $end
$var wire 1 + B3 $end
$var wire 1 , B4 $end
$var wire 1 - B5 $end
$var wire 1 . bitparidade $end
$var reg 1 ! saida $end
$upscope $end
$upscope $end
$upscope $end
$enddefinitions $end
$comment Show the parameter values. $end
$dumpall
$end
#0
$dumpvars
0.
0-
0,
0+
0*
0)
1(
1'
0&
0%
1$
1#
1"
1!
$end
#100000
1&
1.
1-
#200000
0#
1%
0(
0-
1,
#300000
1#
0%
0&
0'
1(
0.
1-
#400000
1&
1'
0(
1.
0-
0,
1+
#500000
1%
1(
0.
1-
#600000
0"
0-
1,
#700000
0#
0%
0'
1.
1-
#800000
1"
1#
1'
0(
0-
0,
0+
1*
#900000
0$
1%
0'
1(
0.
1-
#1000000
0"
1$
0&
0(
0-
1,
#1100000
0#
1&
1.
1-
#1200000
1"
1#
0$
0%
0.
0-
0,
1+
#1300000
1%
1'
1(
1.
1-
#1400000
0'
0-
1,
#1500000
0"
0#
1$
1'
0.
1-
#1600000
1"
0$
1.
0-
0,
0+
0*
1)
#1700000
1#
0(
0.
1-
#1800000
1$
1(
0-
1,
#1900000
0$
1.
1-
#2000000
0#
0%
0&
0'
0(
0!
1"
0.
1+
1*
#2100000
1.
0-
0,
0*
#2200000
0.
1-
